agf/ArticleGenerator.py
agf/__init__.py
agf-0.1.dist-info/METADATA
agf-0.1.dist-info/WHEEL
agf-0.1.dist-info/top_level.txt
agf-0.1.dist-info/RECORD
